sendmail/__init__.py
sendmail/__main__.py
sendmail/sendmail.py
climailsystem-0.dist-info/LICENSE
climailsystem-0.dist-info/METADATA
climailsystem-0.dist-info/WHEEL
climailsystem-0.dist-info/entry_points.txt
climailsystem-0.dist-info/top_level.txt
climailsystem-0.dist-info/RECORD
